LICENSE
MANIFEST.in
README
requirements.pip
setup.py
jmbo_your_words.egg-info/PKG-INFO
jmbo_your_words.egg-info/SOURCES.txt
jmbo_your_words.egg-info/dependency_links.txt
jmbo_your_words.egg-info/requires.txt
jmbo_your_words.egg-info/top_level.txt
jmboyourwords/__init__.py
jmboyourwords/admin.py
jmboyourwords/forms.py
jmboyourwords/managers.py
jmboyourwords/models.py
jmboyourwords/tests.py
jmboyourwords/urls.py
jmboyourwords/views.py
jmboyourwords/management/__init__.py
jmboyourwords/management/commands/__init__.py
jmboyourwords/management/commands/your_words_content_scheduler.py
jmboyourwords/migrations/0001_initial.py
jmboyourwords/migrations/0002_auto__del_field_yourstorycompetition_source_name__del_field_yourstoryc.py
jmboyourwords/migrations/0003_auto__add_field_yourstorycompetition_terms_and_conditions.py
jmboyourwords/migrations/__init__.py
jmboyourwords/templates/yourwords/your_story.html
jmboyourwords/templatetags/__init__.py
jmboyourwords/templatetags/your_words_tags.py